MANIFEST.in
setup.py
my_ctl/__init__.py
my_ctl/my_ctl.cp39-win_amd64.pyd
my_ctl.egg-info/PKG-INFO
my_ctl.egg-info/SOURCES.txt
my_ctl.egg-info/dependency_links.txt
my_ctl.egg-info/entry_points.txt
my_ctl.egg-info/requires.txt
my_ctl.egg-info/top_level.txt